baidu_translate_py/__init__.py
baidu_translate_py/baidu_translate.py
baidu_translate_py/dt.py
baidu_translate_py/niu_translate.py
baidu_translate_py/test_translate.py
baidu_translate_py-0.1.0.dist-info/WHEEL
baidu_translate_py-0.1.0.dist-info/METADATA
baidu_translate_py-0.1.0.dist-info/RECORD
